simd_r_drive/__init__.py
simd_r_drive/py.typed
simd_r_drive/simd_r_drive.cpython-313-x86_64-linux-gnu.so
simd_r_drive/simd_r_drive.pyi
simd_r_drive_py-0.5.0a0.dist-info/METADATA
simd_r_drive_py-0.5.0a0.dist-info/WHEEL
simd_r_drive_py-0.5.0a0.dist-info/RECORD
simd_r_drive_py-0.5.0a0.dist-info/licenses/LICENSE
