Metadata-Version: 2.4
Name: simd-r-drive-py
Version: 0.5.0a0
Classifier: Development Status :: 3 - Alpha
Classifier: Intended Audience :: Developers
Classifier: License :: OSI Approved :: Apache Software License
Classifier: Topic :: Software Development :: Libraries :: Python Modules
Classifier: Topic :: System :: Filesystems
Classifier: Topic :: Database :: Database Engines/Servers
Classifier: Programming Language :: Rust
Classifier: Programming Language :: Python :: Implementation :: CPython
Classifier: Programming Language :: Python
Classifier: Programming Language :: Python :: 3.10
Classifier: Programming Language :: Python :: 3.11
Classifier: Programming Language :: Python :: 3.12
Classifier: Programming Language :: Python :: 3.13
Classifier: Operating System :: POSIX :: Linux
Classifier: Operating System :: MacOS
License-File: LICENSE
Summary: SIMD-optimized append-only schema-less storage engine. Key-based binary storage in a single-file storage container.
Keywords: storage-engine,binary-storage,append-only,simd,mmap
License: Apache-2.0
